.DS_Store
EDA/__init__.py
EDA/eda.py
EDA_recordk/__init__.py
EDA_recordk/eda.py
EDA_recordk-1.0.5.dist-info/METADATA
EDA_recordk-1.0.5.dist-info/WHEEL
EDA_recordk-1.0.5.dist-info/top_level.txt
EDA_recordk-1.0.5.dist-info/RECORD
